joyit_mfrc522/MFRC522.py
joyit_mfrc522/SimpleMFRC522.py
joyit_mfrc522/__init__.py
joyit_mfrc522-0.1.0.dist-info/LICENSE
joyit_mfrc522-0.1.0.dist-info/METADATA
joyit_mfrc522-0.1.0.dist-info/WHEEL
joyit_mfrc522-0.1.0.dist-info/top_level.txt
joyit_mfrc522-0.1.0.dist-info/RECORD
