Metadata-Version: 2.1
Name: joyit_mfrc522
Version: 0.1.0
Summary: A library to integrate the MFRC522 RFID readers with the Raspberry Pi
Home-page: https://github.com/tct123/MFRC522-python
Author: Pi My Life Up
Author-email: support@pimylifeup.com
Classifier: Programming Language :: Python :: 2.7
Classifier: Programming Language :: Python :: 3
Classifier: License :: OSI Approved :: GNU Lesser General Public License v3 or later (LGPLv3+)
Classifier: Operating System :: POSIX :: Linux
Classifier: Topic :: System :: Hardware
License-File: LICENSE
Requires-Dist: gpiozero
Requires-Dist: spidev
